medizinfuchs/__init__.py
medizinfuchs/runner.py
medizinfuchs/spider.py
medizinfuchs_mosalam-0.0.1.dist-info/LICENSE
medizinfuchs_mosalam-0.0.1.dist-info/METADATA
medizinfuchs_mosalam-0.0.1.dist-info/WHEEL
medizinfuchs_mosalam-0.0.1.dist-info/top_level.txt
medizinfuchs_mosalam-0.0.1.dist-info/RECORD
