Metadata-Version: 2.1
Name: medizinfuchs-mosalam
Version: 0.0.1
Summary: A package to scrap medical products from medizinfuchs.de
Home-page: https://github.com/m7salam/medizinfuchs-spider
Author: Mohamed Hussein(Mo Salam)
Author-email: mosalam208@gmail.com
License: UNKNOWN
Platform: UNKNOWN
Classifier: Programming Language :: Python :: 3
Classifier: License :: OSI Approved :: MIT License
Classifier: Operating System :: OS Independent
Classifier: Development Status :: 2 - Pre-Alpha
Requires-Python: >=3.6
